final_class/__init__.py
final_class/__init__.pyi
final_class/final_class.py
final_class/py.typed
final_class-0.2.0.dist-info/LICENSE
final_class-0.2.0.dist-info/WHEEL
final_class-0.2.0.dist-info/METADATA
final_class-0.2.0.dist-info/RECORD
